svault/__init__.py
svault/vault.py
svault/vault_server.py
s_vault-0.0.2.dist-info/METADATA
s_vault-0.0.2.dist-info/WHEEL
s_vault-0.0.2.dist-info/top_level.txt
s_vault-0.0.2.dist-info/RECORD
