Metadata-Version: 2.1
Name: s-vault
Version: 0.0.2
Summary: Simple vault server
Home-page: https://github.com/eldad1221/s-vault
Author: Eldad Bishari
Author-email: eldad@1221tlv.org
License: UNKNOWN
Platform: UNKNOWN
Classifier: Programming Language :: Python :: 3
Classifier: License :: OSI Approved :: MIT License
Classifier: Operating System :: OS Independent
Requires-Python: >=3.7
Requires-Dist: quickbe
Requires-Dist: GitPython (==3.1.24)
Requires-Dist: cryptography (==35.0.0)
